{
  "skill": "book-style",
  "items": [
    { "id": "no-colons-in-prose", "description": "No colon in prose; YAML, code, and URLs exempt.", "severity": "high", "blocking": true },
    { "id": "no-mid-sentence-emdash-list", "description": "No mid sentence em dash introducing a list or appositive.", "severity": "high", "blocking": true },
    { "id": "no-mechanical-takeaway-formulae", "description": "No slot filler openers; transitions specific to the substance above.", "severity": "high", "blocking": true },
    { "id": "no-meta-callouts-in-prose", "description": "No decorative pullquotes or signpost subheaders; pedagogical callouts kept.", "severity": "high", "blocking": true },
    { "id": "minimal-restatement-connectives", "description": "Drugim rijecima and kin at most once per chapter.", "severity": "medium", "blocking": false },
    { "id": "title-uses-emdash-separator", "description": "Chapter title separator is an em dash, not a colon.", "severity": "medium", "blocking": true },
    { "id": "bold-for-first-mention-only", "description": "Bold only for first mention concept anchors.", "severity": "low", "blocking": false }
  ]
}
